causaldata/__init__.py
causaldata/Mroz/Mroz.csv
causaldata/Mroz/__init__.py
causaldata/Mroz/data.py
causaldata/abortion/__init__.py
causaldata/abortion/abortion.dta
causaldata/abortion/data.py
causaldata/adult_services/__init__.py
causaldata/adult_services/adult_services.dta
causaldata/adult_services/data.py
causaldata/auto/__init__.py
causaldata/auto/auto.dta
causaldata/auto/data.py
causaldata/avocado/__init__.py
causaldata/avocado/avocado.dta
causaldata/avocado/data.py
causaldata/black_politicians/__init__.py
causaldata/black_politicians/black_politicians.csv
causaldata/black_politicians/data.py
causaldata/castle/__init__.py
causaldata/castle/castle.dta
causaldata/castle/data.py
causaldata/ccdrug/__init__.py
causaldata/ccdrug/ccdrug.dta
causaldata/ccdrug/data.py
causaldata/close_college/__init__.py
causaldata/close_college/close_college.dta
causaldata/close_college/data.py
causaldata/close_elections_lmb/__init__.py
causaldata/close_elections_lmb/close_elections_lmb.dta
causaldata/close_elections_lmb/data.py
causaldata/cps_mixtape/__init__.py
causaldata/cps_mixtape/cps_mixtape.dta
causaldata/cps_mixtape/data.py
causaldata/credit_cards/__init__.py
causaldata/credit_cards/credit_cards.dta
causaldata/credit_cards/data.py
causaldata/gapminder/__init__.py
causaldata/gapminder/data.py
causaldata/gapminder/gapminder.csv
causaldata/google_stock/__init__.py
causaldata/google_stock/data.py
causaldata/google_stock/google_stock_data.csv
causaldata/gov_transfers/Government_Transfers_RDD_Data.csv
causaldata/gov_transfers/__init__.py
causaldata/gov_transfers/data.py
causaldata/gov_transfers_density/Government_Transfers_McCrary.csv
causaldata/gov_transfers_density/__init__.py
causaldata/gov_transfers_density/data.py
causaldata/greek_data/__init__.py
causaldata/greek_data/data.py
causaldata/greek_data/greek_data.dta
causaldata/mortgages/__init__.py
causaldata/mortgages/data.py
causaldata/mortgages/fetter_mortgages.csv
causaldata/nhefs/__init__.py
causaldata/nhefs/data.py
causaldata-0.1.4.dist-info/METADATA
causaldata-0.1.4.dist-info/WHEEL
causaldata-0.1.4.dist-info/top_level.txt
causaldata-0.1.4.dist-info/RECORD
