Metadata-Version: 2.1
Name: causaldata
Version: 0.1.4
Summary: Example Data Sets for Causal Inference
Author: Nick Huntington-Klein
Author-email: nhuntington-klein@seattleu.edu
License: MIT license
Keywords: python,causal inference,example data
Classifier: Development Status :: 3 - Alpha
Classifier: Intended Audience :: Education
Classifier: Programming Language :: Python :: 2
Classifier: Programming Language :: Python :: 3
Classifier: Operating System :: MacOS :: MacOS X
Classifier: Operating System :: Microsoft :: Windows
Requires-Dist: statsmodels
Requires-Dist: pandas
